eip712_structs/__init__.py
eip712_structs/domain_separator.py
eip712_structs/py.typed
eip712_structs/struct.py
eip712_structs/types.py
eip712_structs_ng-2.0.1.dist-info/METADATA
eip712_structs_ng-2.0.1.dist-info/WHEEL
eip712_structs_ng-2.0.1.dist-info/licenses/LICENSE
eip712_structs_ng-2.0.1.dist-info/RECORD
