Metadata-Version: 2.1
Name: eip712-structs-ng
Version: 2.0.1
Summary: A Python interface for EIP-712 struct construction.
Project-URL: Source, https://github.com/BoboTiG/py-eip712-structs-ng
Project-URL: Tracker, https://github.com/BoboTiG/py-eip712-structs-ng/issues
Project-URL: Released Versions, https://github.com/BoboTiG/py-eip712-structs-ng/releases
Author: AJ Grubbs
Author-email: Mickaël Schoentgen <contact@tiger-222.fr>
Maintainer-email: Mickaël Schoentgen <contact@tiger-222.fr>
License: MIT License
License-File: LICENSE
Keywords: eip712,ethereum,solidity
Classifier: Development Status :: 5 - Production/Stable
Classifier: Intended Audience :: Developers
Classifier: Intended Audience :: Information Technology
Classifier: License :: OSI Approved :: MIT License
Classifier: Programming Language :: Python
Classifier: Programming Language :: Python :: 3
Classifier: Programming Language :: Python :: 3 :: Only
Classifier: Programming Language :: Python :: 3.8
Classifier: Programming Language :: Python :: 3.9
Classifier: Programming Language :: Python :: 3.10
Classifier: Programming Language :: Python :: 3.11
Classifier: Programming Language :: Python :: 3.12
Classifier: Programming Language :: Python :: Implementation :: CPython
Requires-Python: >=3.8
Requires-Dist: eth-utils<3,>=2.3.1
Provides-Extra: dev
Requires-Dist: build; extra == 'dev'
Requires-Dist: twine; extra == 'dev'
Provides-Extra: tests
Requires-Dist: eth-tester==0.10.0b1; extra == 'tests'
Requires-Dist: mypy; extra == 'tests'
Requires-Dist: py-evm==0.8.0b1; extra == 'tests'
Requires-Dist: py-solc-x==2.0.2; extra == 'tests'
Requires-Dist: pytest; extra == 'tests'
Requires-Dist: pytest-cov; extra == 'tests'
Requires-Dist: requests; extra == 'tests'
Requires-Dist: ruff; extra == 'tests'
Requires-Dist: web3<7,>=6.3.0; extra == 'tests'
